dijkstra3d.cpython-310-x86_64-linux-gnu.so
dijkstra3d-1.15.2.dist-info/METADATA
dijkstra3d-1.15.2.dist-info/WHEEL
dijkstra3d-1.15.2.dist-info/top_level.txt
dijkstra3d-1.15.2.dist-info/RECORD
dijkstra3d-1.15.2.dist-info/licenses/AUTHORS
dijkstra3d-1.15.2.dist-info/licenses/LICENSE
